cytonic/__init__.py
cytonic/py.typed
cytonic/codegen/__init__.py
cytonic/codegen/python.py
cytonic/contrib/__init__.py
cytonic/contrib/fastapi.py
cytonic/description/__init__.py
cytonic/description/_decorators.py
cytonic/description/_description.py
cytonic/model/__init__.py
cytonic/model/_auth.py
cytonic/model/_endpoint.py
cytonic/model/_error.py
cytonic/model/_http_path.py
cytonic/model/_module.py
cytonic/model/_param.py
cytonic/model/_project.py
cytonic/model/_type.py
cytonic/runtime/__init__.py
cytonic/runtime/auth.py
cytonic/runtime/exceptions.py
cytonic/test/__init__.py
cytonic/test/_http_path_test.py
cytonic/test/_service_description_test.py
cytonic-0.2.0.dist-info/LICENSE
cytonic-0.2.0.dist-info/METADATA
cytonic-0.2.0.dist-info/WHEEL
cytonic-0.2.0.dist-info/entry_points.txt
cytonic-0.2.0.dist-info/top_level.txt
cytonic-0.2.0.dist-info/RECORD
