Metadata-Version: 2.1
Name: cytonic
Version: 0.2.0
Summary: A Python framework to define REST APIs and automatically generate server side bindings and clients.
Home-page: https://gitea.nkl.st/_/cytonic
Author: Niklas Rosenstein
Author-email: rosensteinniklas@gmail.com
License: MIT
Platform: UNKNOWN
Requires-Python: >=3.10.0,<4.0.0
Requires-Dist: databind.json (<2.0.0,>=1.3.2)
Requires-Dist: nr.util (<1.0.0,>=0.2.1)
Requires-Dist: pyyaml (<6.0.0,>=5.4.0)
Provides-Extra: fastapi
Requires-Dist: fastapi (<1.0.0,>=0.70.1) ; extra == 'fastapi'
Provides-Extra: test
Requires-Dist: types-pyyaml ; extra == 'test'
